bytedance_vgfm_ml_ocr_processor/__init__.py
bytedance_vgfm_ml_ocr_processor-0.0.1.dist-info/METADATA
bytedance_vgfm_ml_ocr_processor-0.0.1.dist-info/WHEEL
bytedance_vgfm_ml_ocr_processor-0.0.1.dist-info/top_level.txt
bytedance_vgfm_ml_ocr_processor-0.0.1.dist-info/RECORD
